setup.py
abhi_probability/Binomialdistribution.py
abhi_probability/Gaussiandistribution.py
abhi_probability/Generaldistribution.py
abhi_probability/__init__.py
abhi_probability.egg-info/PKG-INFO
abhi_probability.egg-info/SOURCES.txt
abhi_probability.egg-info/dependency_links.txt
abhi_probability.egg-info/not-zip-safe
abhi_probability.egg-info/top_level.txt