Metadata-Version: 1.0
Name: abhi-probability
Version: 0.1
Summary: Gaussian and Binomial distributions
Home-page: UNKNOWN
Author: Abhi G
Author-email: abhi@yahoo.com
License: UNKNOWN
Platform: UNKNOWN
